virus/__init__.py
virus/test.py
uz_virus-0.0.4.dist-info/METADATA
uz_virus-0.0.4.dist-info/WHEEL
uz_virus-0.0.4.dist-info/top_level.txt
uz_virus-0.0.4.dist-info/RECORD
