Metadata-Version: 2.1
Name: uz_virus
Version: 0.0.4
Summary: siz bu kutubxona orqali virus yarata olasiz
Author: Salohiddin
Author-email: salohiddinsalohiddin123@gmail.com
Classifier: Programming Language :: Python :: 3
Classifier: License :: OSI Approved :: MIT License
Classifier: Operating System :: OS Independent
Requires-Python: >=3.6
